kappaml_core/__init__.py
kappaml_core/cli.py
kappaml_core/datasets/__init__.py
kappaml_core/datasets/movielens25M.py
kappaml_core/meta/__init__.py
kappaml_core/meta/base.py
kappaml_core/meta/meta_classifier.py
kappaml_core/meta/meta_regressor.py
kappaml_core-0.0.6.dist-info/licenses/LICENSE.txt
kappaml_core-0.0.6.dist-info/METADATA
kappaml_core-0.0.6.dist-info/WHEEL
kappaml_core-0.0.6.dist-info/entry_points.txt
kappaml_core-0.0.6.dist-info/top_level.txt
kappaml_core-0.0.6.dist-info/RECORD
