Metadata-Version: 2.4
Name: kappaml-core
Version: 0.0.6
Summary: Online automated machine learning algorithms from KappaML
Home-page: https://github.com/KappaML/kappaml-core
Author: Alex Imbrea
Author-email: alex@kappaml.com
License: Apache-2.0
Project-URL: Documentation, https://kappaml-core.readthedocs.io/en/latest
Project-URL: Source, https://github.com/KappaML/kappaml-core
Platform: any
Classifier: Development Status :: 4 - Beta
Classifier: Programming Language :: Python
License-File: LICENSE.txt
Requires-Dist: importlib-metadata; python_version < "3.8"
Requires-Dist: river>=0.22.0
Requires-Dist: pymfe>=0.4.3
Provides-Extra: testing
Requires-Dist: setuptools; extra == "testing"
Requires-Dist: pytest; extra == "testing"
Requires-Dist: pytest-cov; extra == "testing"
Dynamic: license-file
